pyquestion/__init__.py
pyquestions-0.1.0.dist-info/LICENSE
pyquestions-0.1.0.dist-info/METADATA
pyquestions-0.1.0.dist-info/WHEEL
pyquestions-0.1.0.dist-info/top_level.txt
pyquestions-0.1.0.dist-info/RECORD
