Metadata-Version: 2.1
Name: pyquestions
Version: 0.1.0
Summary: Return a variety of Python problem/question to solve
Home-page: https://github.com/onkarhanchate14/pyquestion/
Author: Onkar Hanchate
Author-email: onkarhanchate14@gmail.com
License: Apache License 2.0
Platform: UNKNOWN
Requires-Dist: random
